README.md
setup.py
pulumi_azure_static_website/__init__.py
pulumi_azure_static_website/_utilities.py
pulumi_azure_static_website/provider.py
pulumi_azure_static_website/pulumi-plugin.json
pulumi_azure_static_website/py.typed
pulumi_azure_static_website/website.py
pulumi_azure_static_website.egg-info/PKG-INFO
pulumi_azure_static_website.egg-info/SOURCES.txt
pulumi_azure_static_website.egg-info/dependency_links.txt
pulumi_azure_static_website.egg-info/not-zip-safe
pulumi_azure_static_website.egg-info/requires.txt
pulumi_azure_static_website.egg-info/top_level.txt