Metadata-Version: 2.1
Name: pulumi-azure-static-website
Version: 0.0.0
Summary: UNKNOWN
Home-page: UNKNOWN
License: UNKNOWN
Platform: UNKNOWN
